authlib/__init__.py
authlib/_compat.py
authlib/backends.py
authlib/base_user.py
authlib/email.py
authlib/facebook.py
authlib/google.py
authlib/roles.py
authlib/twitter.py
authlib/views.py
authlib/admin_oauth/__init__.py
authlib/admin_oauth/urls.py
authlib/admin_oauth/views.py
authlib/admin_oauth/locale/de/LC_MESSAGES/django.mo
authlib/admin_oauth/locale/de/LC_MESSAGES/django.po
authlib/admin_oauth/templates/admin/login.html
authlib/little_auth/__init__.py
authlib/little_auth/admin.py
authlib/little_auth/apps.py
authlib/little_auth/models.py
authlib/little_auth/locale/de/LC_MESSAGES/django.mo
authlib/little_auth/locale/de/LC_MESSAGES/django.po
authlib/little_auth/migrations/0001_initial.py
authlib/little_auth/migrations/0002_user_role.py
authlib/little_auth/migrations/__init__.py
authlib/locale/de/LC_MESSAGES/django.mo
authlib/locale/de/LC_MESSAGES/django.po
django_authlib-0.17.1.dist-info/METADATA
django_authlib-0.17.1.dist-info/WHEEL
django_authlib-0.17.1.dist-info/licenses/LICENSE
django_authlib-0.17.1.dist-info/RECORD
