Metadata-Version: 2.3
Name: django-authlib
Version: 0.17.1
Summary: Authentication utils for Django
Project-URL: Homepage, http://github.com/matthiask/django-authlib/
Author-email: Matthias Kestenholz <mk@feinheit.ch>
License: MIT
License-File: LICENSE
Classifier: Development Status :: 5 - Production/Stable
Classifier: Environment :: Web Environment
Classifier: Framework :: Django
Classifier: License :: OSI Approved :: MIT License
Classifier: Operating System :: OS Independent
Classifier: Programming Language :: Python
Classifier: Programming Language :: Python :: 3 :: Only
Classifier: Programming Language :: Python :: 3.9
Classifier: Programming Language :: Python :: 3.10
Classifier: Programming Language :: Python :: 3.11
Classifier: Programming Language :: Python :: 3.12
Requires-Python: >=3.9
Requires-Dist: requests-oauthlib
Provides-Extra: tests
Requires-Dist: coverage; extra == 'tests'
Requires-Dist: requests-mock; extra == 'tests'
